[{
    "epoch": "tokenassignment",
    "trial": 93,
    "player": "434879340.164261",
    "stage": {
        "stage": 3,
        "step": 2,
        "round": 93
    },
    "timestamp": 1601863223129
}, {
    "epoch": "tokenassignment",
    "trial": 93,
    "player": "998249638.6446189",
    "stage": {
        "stage": 3,
        "step": 2,
        "round": 93
    },
    "timestamp": 1601863223130
}, {
    "time": 1555,
    "timeup": true,
    "done": true,
    "player": "434879340.164261",
    "stage": {
        "stage": 3,
        "step": 2,
        "round": 93
    },
    "timestamp": 1601863224647
}, {
    "time": 1573,
    "timeup": true,
    "done": true,
    "player": "998249638.6446189",
    "stage": {
        "stage": 3,
        "step": 2,
        "round": 93
    },
    "timestamp": 1601863224681
}]