[{
    "epoch": "tokenassignment",
    "trial": 85,
    "player": "255870962.34081462",
    "stage": {
        "stage": 3,
        "step": 2,
        "round": 85
    },
    "timestamp": 1601675019377
}, {
    "epoch": "tokenassignment",
    "trial": 85,
    "player": "582723060.5891216",
    "stage": {
        "stage": 3,
        "step": 2,
        "round": 85
    },
    "timestamp": 1601675019439
}, {
    "time": 1501,
    "timeup": true,
    "done": true,
    "player": "582723060.5891216",
    "stage": {
        "stage": 3,
        "step": 2,
        "round": 85
    },
    "timestamp": 1601675020844
}, {
    "time": 1514,
    "timeup": true,
    "done": true,
    "player": "255870962.34081462",
    "stage": {
        "stage": 3,
        "step": 2,
        "round": 85
    },
    "timestamp": 1601675020848
}]