[{
    "epoch": "tokenassignment",
    "trial": 12,
    "player": "255870962.34081462",
    "stage": {
        "stage": 3,
        "step": 2,
        "round": 12
    },
    "timestamp": 1601673450257
}, {
    "epoch": "tokenassignment",
    "trial": 12,
    "player": "582723060.5891216",
    "stage": {
        "stage": 3,
        "step": 2,
        "round": 12
    },
    "timestamp": 1601673450272
}, {
    "time": 1500,
    "timeup": true,
    "done": true,
    "player": "255870962.34081462",
    "stage": {
        "stage": 3,
        "step": 2,
        "round": 12
    },
    "timestamp": 1601673451757
}, {
    "time": 1509,
    "timeup": true,
    "done": true,
    "player": "582723060.5891216",
    "stage": {
        "stage": 3,
        "step": 2,
        "round": 12
    },
    "timestamp": 1601673451766
}]