[{
    "epoch": "tokenassignment",
    "trial": 20,
    "player": "285910281.7348864",
    "stage": {
        "stage": 3,
        "step": 2,
        "round": 20
    },
    "timestamp": 1601863354682
}, {
    "epoch": "tokenassignment",
    "trial": 20,
    "player": "983111089.8653324",
    "stage": {
        "stage": 3,
        "step": 2,
        "round": 20
    },
    "timestamp": 1601863354752
}, {
    "time": 1509,
    "timeup": true,
    "done": true,
    "player": "285910281.7348864",
    "stage": {
        "stage": 3,
        "step": 2,
        "round": 20
    },
    "timestamp": 1601863356191
}, {
    "time": 1547,
    "timeup": true,
    "done": true,
    "player": "983111089.8653324",
    "stage": {
        "stage": 3,
        "step": 2,
        "round": 20
    },
    "timestamp": 1601863356266
}]