[{
    "epoch": "tokenassignment",
    "trial": 24,
    "player": "631658198.2507914",
    "stage": {
        "stage": 3,
        "step": 2,
        "round": 24
    },
    "timestamp": 1601501425260
}, {
    "epoch": "tokenassignment",
    "trial": 24,
    "player": "3781862.4180374625",
    "stage": {
        "stage": 3,
        "step": 2,
        "round": 24
    },
    "timestamp": 1601501425353
}, {
    "time": 1501,
    "timeup": true,
    "done": true,
    "player": "631658198.2507914",
    "stage": {
        "stage": 3,
        "step": 2,
        "round": 24
    },
    "timestamp": 1601501426766
}, {
    "time": 1593,
    "timeup": true,
    "done": true,
    "player": "3781862.4180374625",
    "stage": {
        "stage": 3,
        "step": 2,
        "round": 24
    },
    "timestamp": 1601501426888
}]