[{
    "epoch": "tokenassignment",
    "trial": 87,
    "player": "631658198.2507914",
    "stage": {
        "stage": 3,
        "step": 2,
        "round": 87
    },
    "timestamp": 1601502979302
}, {
    "epoch": "tokenassignment",
    "trial": 87,
    "player": "3781862.4180374625",
    "stage": {
        "stage": 3,
        "step": 2,
        "round": 87
    },
    "timestamp": 1601502979412
}, {
    "time": 1501,
    "timeup": true,
    "done": true,
    "player": "631658198.2507914",
    "stage": {
        "stage": 3,
        "step": 2,
        "round": 87
    },
    "timestamp": 1601502980809
}, {
    "time": 1685,
    "timeup": true,
    "done": true,
    "player": "3781862.4180374625",
    "stage": {
        "stage": 3,
        "step": 2,
        "round": 87
    },
    "timestamp": 1601502980988
}]