[{
    "epoch": "tokenassignment",
    "trial": 67,
    "player": "763803746.6497123",
    "stage": {
        "stage": 3,
        "step": 2,
        "round": 67
    },
    "timestamp": 1601780695504
}, {
    "epoch": "tokenassignment",
    "trial": 67,
    "player": "267792479.30127493",
    "stage": {
        "stage": 3,
        "step": 2,
        "round": 67
    },
    "timestamp": 1601780695511
}, {
    "time": 1518,
    "timeup": true,
    "done": true,
    "player": "763803746.6497123",
    "stage": {
        "stage": 3,
        "step": 2,
        "round": 67
    },
    "timestamp": 1601780696985
}, {
    "time": 1586,
    "timeup": true,
    "done": true,
    "player": "267792479.30127493",
    "stage": {
        "stage": 3,
        "step": 2,
        "round": 67
    },
    "timestamp": 1601780697044
}]