[{
    "epoch": "tokenassignment",
    "trial": 68,
    "player": "401457900.6395202",
    "stage": {
        "stage": 3,
        "step": 2,
        "round": 68
    },
    "timestamp": 1601649945476
}, {
    "epoch": "tokenassignment",
    "trial": 68,
    "player": "258854421.63748175",
    "stage": {
        "stage": 3,
        "step": 2,
        "round": 68
    },
    "timestamp": 1601649945485
}, {
    "time": 1501,
    "timeup": true,
    "done": true,
    "player": "401457900.6395202",
    "stage": {
        "stage": 3,
        "step": 2,
        "round": 68
    },
    "timestamp": 1601649946978
}, {
    "time": 1502,
    "timeup": true,
    "done": true,
    "player": "258854421.63748175",
    "stage": {
        "stage": 3,
        "step": 2,
        "round": 68
    },
    "timestamp": 1601649946987
}]