[{
    "epoch": "tokenassignment",
    "trial": 35,
    "player": "751999360.1144462",
    "stage": {
        "stage": 3,
        "step": 2,
        "round": 35
    },
    "timestamp": 1601870693607
}, {
    "epoch": "tokenassignment",
    "trial": 35,
    "player": "989977360.2260797",
    "stage": {
        "stage": 3,
        "step": 2,
        "round": 35
    },
    "timestamp": 1601870693611
}, {
    "time": 1508,
    "timeup": true,
    "done": true,
    "player": "751999360.1144462",
    "stage": {
        "stage": 3,
        "step": 2,
        "round": 35
    },
    "timestamp": 1601870695091
}, {
    "time": 1530,
    "timeup": true,
    "done": true,
    "player": "989977360.2260797",
    "stage": {
        "stage": 3,
        "step": 2,
        "round": 35
    },
    "timestamp": 1601870695125
}]