[{
    "epoch": "tokenassignment",
    "trial": 74,
    "player": "239801528.72965866",
    "stage": {
        "stage": 3,
        "step": 2,
        "round": 74
    },
    "timestamp": 1601672147528
}, {
    "epoch": "tokenassignment",
    "trial": 74,
    "player": "939154983.0786927",
    "stage": {
        "stage": 3,
        "step": 2,
        "round": 74
    },
    "timestamp": 1601672147554
}, {
    "time": 1516,
    "timeup": true,
    "done": true,
    "player": "939154983.0786927",
    "stage": {
        "stage": 3,
        "step": 2,
        "round": 74
    },
    "timestamp": 1601672149040
}, {
    "time": 1555,
    "timeup": true,
    "done": true,
    "player": "239801528.72965866",
    "stage": {
        "stage": 3,
        "step": 2,
        "round": 74
    },
    "timestamp": 1601672149041
}]