[{
    "epoch": "tokenassignment",
    "trial": 12,
    "player": "822259815.5369978",
    "stage": {
        "stage": 2,
        "step": 2,
        "round": 12
    },
    "timestamp": 1602037445938
}, {
    "epoch": "tokenassignment",
    "trial": 12,
    "player": "729193078.2804246",
    "stage": {
        "stage": 2,
        "step": 2,
        "round": 12
    },
    "timestamp": 1602037445946
}, {
    "time": 1505,
    "timeup": true,
    "done": true,
    "player": "822259815.5369978",
    "stage": {
        "stage": 2,
        "step": 2,
        "round": 12
    },
    "timestamp": 1602037447442
}, {
    "time": 1501,
    "timeup": true,
    "done": true,
    "player": "729193078.2804246",
    "stage": {
        "stage": 2,
        "step": 2,
        "round": 12
    },
    "timestamp": 1602037447448
}]