[{
    "epoch": "tokenassignment",
    "trial": 58,
    "player": "117848820.7406192",
    "stage": {
        "stage": 3,
        "step": 2,
        "round": 58
    },
    "timestamp": 1601570220973
}, {
    "epoch": "tokenassignment",
    "trial": 58,
    "player": "70435140.28329478",
    "stage": {
        "stage": 3,
        "step": 2,
        "round": 58
    },
    "timestamp": 1601570221056
}, {
    "time": 1502,
    "timeup": true,
    "done": true,
    "player": "117848820.7406192",
    "stage": {
        "stage": 3,
        "step": 2,
        "round": 58
    },
    "timestamp": 1601570222478
}, {
    "time": 1569,
    "timeup": true,
    "done": true,
    "player": "70435140.28329478",
    "stage": {
        "stage": 3,
        "step": 2,
        "round": 58
    },
    "timestamp": 1601570222561
}]