[{
    "epoch": "tokenassignment",
    "trial": 9,
    "player": "726787695.4439346",
    "stage": {
        "stage": 3,
        "step": 2,
        "round": 9
    },
    "timestamp": 1601570810500
}, {
    "epoch": "tokenassignment",
    "trial": 9,
    "player": "147297625.5973355",
    "stage": {
        "stage": 3,
        "step": 2,
        "round": 9
    },
    "timestamp": 1601570810512
}, {
    "time": 1512,
    "timeup": true,
    "done": true,
    "player": "726787695.4439346",
    "stage": {
        "stage": 3,
        "step": 2,
        "round": 9
    },
    "timestamp": 1601570811980
}, {
    "time": 1500,
    "timeup": true,
    "done": true,
    "player": "147297625.5973355",
    "stage": {
        "stage": 3,
        "step": 2,
        "round": 9
    },
    "timestamp": 1601570811996
}]