[{
    "epoch": "tokenassignment",
    "trial": 40,
    "player": "867664509.7333224",
    "stage": {
        "stage": 3,
        "step": 2,
        "round": 40
    },
    "timestamp": 1601576999727
}, {
    "epoch": "tokenassignment",
    "trial": 40,
    "player": "129259589.38362703",
    "stage": {
        "stage": 3,
        "step": 2,
        "round": 40
    },
    "timestamp": 1601576999734
}, {
    "time": 1501,
    "timeup": true,
    "done": true,
    "player": "867664509.7333224",
    "stage": {
        "stage": 3,
        "step": 2,
        "round": 40
    },
    "timestamp": 1601577001235
}, {
    "time": 1538,
    "timeup": true,
    "done": true,
    "player": "129259589.38362703",
    "stage": {
        "stage": 3,
        "step": 2,
        "round": 40
    },
    "timestamp": 1601577001249
}]