[{
    "epoch": "tokenassignment",
    "trial": 28,
    "player": "975763958.4196161",
    "stage": {
        "stage": 3,
        "step": 2,
        "round": 28
    },
    "timestamp": 1601933548273
}, {
    "epoch": "tokenassignment",
    "trial": 28,
    "player": "109196073.45261784",
    "stage": {
        "stage": 3,
        "step": 2,
        "round": 28
    },
    "timestamp": 1601933548281
}, {
    "time": 1501,
    "timeup": true,
    "done": true,
    "player": "975763958.4196161",
    "stage": {
        "stage": 3,
        "step": 2,
        "round": 28
    },
    "timestamp": 1601933549769
}, {
    "time": 1501,
    "timeup": true,
    "done": true,
    "player": "109196073.45261784",
    "stage": {
        "stage": 3,
        "step": 2,
        "round": 28
    },
    "timestamp": 1601933549783
}]