[{
    "epoch": "tokenassignment",
    "trial": 11,
    "player": "109196073.45261784",
    "stage": {
        "stage": 2,
        "step": 2,
        "round": 11
    },
    "timestamp": 1601932857144
}, {
    "epoch": "tokenassignment",
    "trial": 11,
    "player": "975763958.4196161",
    "stage": {
        "stage": 2,
        "step": 2,
        "round": 11
    },
    "timestamp": 1601932857148
}, {
    "time": 1500,
    "timeup": true,
    "done": true,
    "player": "975763958.4196161",
    "stage": {
        "stage": 2,
        "step": 2,
        "round": 11
    },
    "timestamp": 1601932858643
}, {
    "time": 1500,
    "timeup": true,
    "done": true,
    "player": "109196073.45261784",
    "stage": {
        "stage": 2,
        "step": 2,
        "round": 11
    },
    "timestamp": 1601932858653
}]