[{
    "epoch": "tokenassignment",
    "trial": 75,
    "player": "425458209.3670143",
    "stage": {
        "stage": 3,
        "step": 2,
        "round": 75
    },
    "timestamp": 1601654883905
}, {
    "epoch": "tokenassignment",
    "trial": 75,
    "player": "457691627.44913805",
    "stage": {
        "stage": 3,
        "step": 2,
        "round": 75
    },
    "timestamp": 1601654883984
}, {
    "time": 1520,
    "timeup": true,
    "done": true,
    "player": "425458209.3670143",
    "stage": {
        "stage": 3,
        "step": 2,
        "round": 75
    },
    "timestamp": 1601654885406
}, {
    "time": 1515,
    "timeup": true,
    "done": true,
    "player": "457691627.44913805",
    "stage": {
        "stage": 3,
        "step": 2,
        "round": 75
    },
    "timestamp": 1601654885458
}]