[{
    "epoch": "tokenassignment",
    "trial": 14,
    "player": "963150180.1044165",
    "stage": {
        "stage": 3,
        "step": 2,
        "round": 14
    },
    "timestamp": 1601880239428
}, {
    "epoch": "tokenassignment",
    "trial": 14,
    "player": "41836972.5613541",
    "stage": {
        "stage": 3,
        "step": 2,
        "round": 14
    },
    "timestamp": 1601880239442
}, {
    "time": 1501,
    "timeup": true,
    "done": true,
    "player": "963150180.1044165",
    "stage": {
        "stage": 3,
        "step": 2,
        "round": 14
    },
    "timestamp": 1601880240931
}, {
    "time": 1524,
    "timeup": true,
    "done": true,
    "player": "41836972.5613541",
    "stage": {
        "stage": 3,
        "step": 2,
        "round": 14
    },
    "timestamp": 1601880240972
}]