[{
    "epoch": "tokenassignment",
    "trial": 45,
    "player": "213194772.03010106",
    "stage": {
        "stage": 3,
        "step": 2,
        "round": 45
    },
    "timestamp": 1601862838009
}, {
    "epoch": "tokenassignment",
    "trial": 45,
    "player": "376305546.5030902",
    "stage": {
        "stage": 3,
        "step": 2,
        "round": 45
    },
    "timestamp": 1601862838118
}, {
    "time": 1509,
    "timeup": true,
    "done": true,
    "player": "213194772.03010106",
    "stage": {
        "stage": 3,
        "step": 2,
        "round": 45
    },
    "timestamp": 1601862839492
}, {
    "time": 1622,
    "timeup": true,
    "done": true,
    "player": "376305546.5030902",
    "stage": {
        "stage": 3,
        "step": 2,
        "round": 45
    },
    "timestamp": 1601862839681
}]