[{
    "epoch": "tokenassignment",
    "trial": 52,
    "player": "952568038.1299409",
    "stage": {
        "stage": 3,
        "step": 2,
        "round": 52
    },
    "timestamp": 1601516878445
}, {
    "epoch": "tokenassignment",
    "trial": 52,
    "player": "747877912.9362829",
    "stage": {
        "stage": 3,
        "step": 2,
        "round": 52
    },
    "timestamp": 1601516878469
}, {
    "time": 1530,
    "timeup": true,
    "done": true,
    "player": "747877912.9362829",
    "stage": {
        "stage": 3,
        "step": 2,
        "round": 52
    },
    "timestamp": 1601516879943
}, {
    "time": 1531,
    "timeup": true,
    "done": true,
    "player": "952568038.1299409",
    "stage": {
        "stage": 3,
        "step": 2,
        "round": 52
    },
    "timestamp": 1601516879950
}]