[{
    "epoch": "tokenassignment",
    "trial": 92,
    "player": "320593039.4601901",
    "stage": {
        "stage": 3,
        "step": 2,
        "round": 92
    },
    "timestamp": 1601866361793
}, {
    "epoch": "tokenassignment",
    "trial": 92,
    "player": "875859909.4204751",
    "stage": {
        "stage": 3,
        "step": 2,
        "round": 92
    },
    "timestamp": 1601866361811
}, {
    "time": 1516,
    "timeup": true,
    "done": true,
    "player": "875859909.4204751",
    "stage": {
        "stage": 3,
        "step": 2,
        "round": 92
    },
    "timestamp": 1601866363277
}, {
    "time": 1551,
    "timeup": true,
    "done": true,
    "player": "320593039.4601901",
    "stage": {
        "stage": 3,
        "step": 2,
        "round": 92
    },
    "timestamp": 1601866363304
}]