[{
    "epoch": "tokenassignment",
    "trial": 17,
    "player": "320593039.4601901",
    "stage": {
        "stage": 3,
        "step": 2,
        "round": 17
    },
    "timestamp": 1601865034676
}, {
    "epoch": "tokenassignment",
    "trial": 17,
    "player": "875859909.4204751",
    "stage": {
        "stage": 3,
        "step": 2,
        "round": 17
    },
    "timestamp": 1601865034685
}, {
    "time": 1502,
    "timeup": true,
    "done": true,
    "player": "875859909.4204751",
    "stage": {
        "stage": 3,
        "step": 2,
        "round": 17
    },
    "timestamp": 1601865036186
}, {
    "time": 1510,
    "timeup": true,
    "done": true,
    "player": "320593039.4601901",
    "stage": {
        "stage": 3,
        "step": 2,
        "round": 17
    },
    "timestamp": 1601865036203
}]