[{
    "epoch": "tokenassignment",
    "trial": 14,
    "player": "320593039.4601901",
    "stage": {
        "stage": 2,
        "step": 2,
        "round": 14
    },
    "timestamp": 1601864671837
}, {
    "epoch": "tokenassignment",
    "trial": 14,
    "player": "875859909.4204751",
    "stage": {
        "stage": 2,
        "step": 2,
        "round": 14
    },
    "timestamp": 1601864671864
}, {
    "time": 1500,
    "timeup": true,
    "done": true,
    "player": "320593039.4601901",
    "stage": {
        "stage": 2,
        "step": 2,
        "round": 14
    },
    "timestamp": 1601864673346
}, {
    "time": 1504,
    "timeup": true,
    "done": true,
    "player": "875859909.4204751",
    "stage": {
        "stage": 2,
        "step": 2,
        "round": 14
    },
    "timestamp": 1601864673347
}]