[{
    "epoch": "tokenassignment",
    "trial": 14,
    "player": "453632164.23396224",
    "stage": {
        "stage": 2,
        "step": 2,
        "round": 14
    },
    "timestamp": 1601830045990
}, {
    "epoch": "tokenassignment",
    "trial": 14,
    "player": "30609224.35658675",
    "stage": {
        "stage": 2,
        "step": 2,
        "round": 14
    },
    "timestamp": 1601830046025
}, {
    "time": 1500,
    "timeup": true,
    "done": true,
    "player": "453632164.23396224",
    "stage": {
        "stage": 2,
        "step": 2,
        "round": 14
    },
    "timestamp": 1601830047492
}, {
    "time": 1500,
    "timeup": true,
    "done": true,
    "player": "30609224.35658675",
    "stage": {
        "stage": 2,
        "step": 2,
        "round": 14
    },
    "timestamp": 1601830047527
}]