[{
    "epoch": "tokenassignment",
    "trial": 1,
    "player": "630540944.0120066",
    "stage": {
        "stage": 2,
        "step": 2,
        "round": 1
    },
    "timestamp": 1601870582391
}, {
    "epoch": "tokenassignment",
    "trial": 1,
    "player": "999851106.7457676",
    "stage": {
        "stage": 2,
        "step": 2,
        "round": 1
    },
    "timestamp": 1601870582398
}, {
    "time": 1503,
    "timeup": true,
    "done": true,
    "player": "999851106.7457676",
    "stage": {
        "stage": 2,
        "step": 2,
        "round": 1
    },
    "timestamp": 1601870583899
}, {
    "time": 1507,
    "timeup": true,
    "done": true,
    "player": "630540944.0120066",
    "stage": {
        "stage": 2,
        "step": 2,
        "round": 1
    },
    "timestamp": 1601870583908
}]