[{
    "epoch": "tokenassignment",
    "trial": 31,
    "player": "434136457.5369992",
    "stage": {
        "stage": 3,
        "step": 2,
        "round": 31
    },
    "timestamp": 1601851188778
}, {
    "epoch": "tokenassignment",
    "trial": 31,
    "player": "510767751.53291696",
    "stage": {
        "stage": 3,
        "step": 2,
        "round": 31
    },
    "timestamp": 1601851188803
}, {
    "time": 1513,
    "timeup": true,
    "done": true,
    "player": "434136457.5369992",
    "stage": {
        "stage": 3,
        "step": 2,
        "round": 31
    },
    "timestamp": 1601851190276
}, {
    "time": 1545,
    "timeup": true,
    "done": true,
    "player": "510767751.53291696",
    "stage": {
        "stage": 3,
        "step": 2,
        "round": 31
    },
    "timestamp": 1601851190319
}]