[{
    "epoch": "tokenassignment",
    "trial": 35,
    "player": "475060613.3404436",
    "stage": {
        "stage": 3,
        "step": 2,
        "round": 35
    },
    "timestamp": 1601515944933
}, {
    "epoch": "tokenassignment",
    "trial": 35,
    "player": "161558744.709835",
    "stage": {
        "stage": 3,
        "step": 2,
        "round": 35
    },
    "timestamp": 1601515945056
}, {
    "time": 1521,
    "timeup": true,
    "done": true,
    "player": "475060613.3404436",
    "stage": {
        "stage": 3,
        "step": 2,
        "round": 35
    },
    "timestamp": 1601515946427
}, {
    "time": 1571,
    "timeup": true,
    "done": true,
    "player": "161558744.709835",
    "stage": {
        "stage": 3,
        "step": 2,
        "round": 35
    },
    "timestamp": 1601515946570
}]