[{
    "epoch": "tokenassignment",
    "trial": 58,
    "player": "475060613.3404436",
    "stage": {
        "stage": 3,
        "step": 2,
        "round": 58
    },
    "timestamp": 1601516332872
}, {
    "epoch": "tokenassignment",
    "trial": 58,
    "player": "161558744.709835",
    "stage": {
        "stage": 3,
        "step": 2,
        "round": 58
    },
    "timestamp": 1601516332944
}, {
    "time": 1517,
    "timeup": true,
    "done": true,
    "player": "475060613.3404436",
    "stage": {
        "stage": 3,
        "step": 2,
        "round": 58
    },
    "timestamp": 1601516334353
}, {
    "time": 1615,
    "timeup": true,
    "done": true,
    "player": "161558744.709835",
    "stage": {
        "stage": 3,
        "step": 2,
        "round": 58
    },
    "timestamp": 1601516334531
}]