[{
    "epoch": "tokenassignment",
    "trial": 23,
    "player": "282753604.26056516",
    "stage": {
        "stage": 3,
        "step": 2,
        "round": 23
    },
    "timestamp": 1601867842127
}, {
    "epoch": "tokenassignment",
    "trial": 23,
    "player": "705357522.7977992",
    "stage": {
        "stage": 3,
        "step": 2,
        "round": 23
    },
    "timestamp": 1601867842319
}, {
    "time": 1504,
    "timeup": true,
    "done": true,
    "player": "282753604.26056516",
    "stage": {
        "stage": 3,
        "step": 2,
        "round": 23
    },
    "timestamp": 1601867843613
}, {
    "time": 1557,
    "timeup": true,
    "done": true,
    "player": "705357522.7977992",
    "stage": {
        "stage": 3,
        "step": 2,
        "round": 23
    },
    "timestamp": 1601867843725
}]