[{
    "epoch": "tokenassignment",
    "trial": 15,
    "player": "282753604.26056516",
    "stage": {
        "stage": 3,
        "step": 2,
        "round": 15
    },
    "timestamp": 1601867685068
}, {
    "epoch": "tokenassignment",
    "trial": 15,
    "player": "705357522.7977992",
    "stage": {
        "stage": 3,
        "step": 2,
        "round": 15
    },
    "timestamp": 1601867685113
}, {
    "time": 1502,
    "timeup": true,
    "done": true,
    "player": "282753604.26056516",
    "stage": {
        "stage": 3,
        "step": 2,
        "round": 15
    },
    "timestamp": 1601867686569
}, {
    "time": 1556,
    "timeup": true,
    "done": true,
    "player": "705357522.7977992",
    "stage": {
        "stage": 3,
        "step": 2,
        "round": 15
    },
    "timestamp": 1601867686628
}]