[{
    "epoch": "tokenassignment",
    "trial": 11,
    "player": "282753604.26056516",
    "stage": {
        "stage": 2,
        "step": 2,
        "round": 11
    },
    "timestamp": 1601867237748
}, {
    "epoch": "tokenassignment",
    "trial": 11,
    "player": "705357522.7977992",
    "stage": {
        "stage": 2,
        "step": 2,
        "round": 11
    },
    "timestamp": 1601867237943
}, {
    "time": 1501,
    "timeup": true,
    "done": true,
    "player": "282753604.26056516",
    "stage": {
        "stage": 2,
        "step": 2,
        "round": 11
    },
    "timestamp": 1601867239249
}, {
    "time": 1534,
    "timeup": true,
    "done": true,
    "player": "705357522.7977992",
    "stage": {
        "stage": 2,
        "step": 2,
        "round": 11
    },
    "timestamp": 1601867239334
}]