[{
    "epoch": "tokenassignment",
    "trial": 11,
    "player": "241438868.92088795",
    "stage": {
        "stage": 2,
        "step": 2,
        "round": 11
    },
    "timestamp": 1601867425977
}, {
    "epoch": "tokenassignment",
    "trial": 11,
    "player": "10839658.106395422",
    "stage": {
        "stage": 2,
        "step": 2,
        "round": 11
    },
    "timestamp": 1601867425979
}, {
    "time": 1502,
    "timeup": true,
    "done": true,
    "player": "241438868.92088795",
    "stage": {
        "stage": 2,
        "step": 2,
        "round": 11
    },
    "timestamp": 1601867427492
}, {
    "time": 1501,
    "timeup": true,
    "done": true,
    "player": "10839658.106395422",
    "stage": {
        "stage": 2,
        "step": 2,
        "round": 11
    },
    "timestamp": 1601867427495
}]