[{
    "epoch": "tokenassignment",
    "trial": 86,
    "player": "55082879.827249795",
    "stage": {
        "stage": 3,
        "step": 2,
        "round": 86
    },
    "timestamp": 1601684362367
}, {
    "epoch": "tokenassignment",
    "trial": 86,
    "player": "586908028.0728834",
    "stage": {
        "stage": 3,
        "step": 2,
        "round": 86
    },
    "timestamp": 1601684362384
}, {
    "time": 1516,
    "timeup": true,
    "done": true,
    "player": "55082879.827249795",
    "stage": {
        "stage": 3,
        "step": 2,
        "round": 86
    },
    "timestamp": 1601684363832
}, {
    "time": 1547,
    "timeup": true,
    "done": true,
    "player": "586908028.0728834",
    "stage": {
        "stage": 3,
        "step": 2,
        "round": 86
    },
    "timestamp": 1601684363902
}]