[{
    "epoch": "tokenassignment",
    "trial": 16,
    "player": "653306322.0366257",
    "stage": {
        "stage": 2,
        "step": 2,
        "round": 16
    },
    "timestamp": 1601658463926
}, {
    "epoch": "tokenassignment",
    "trial": 16,
    "player": "861983579.062231",
    "stage": {
        "stage": 2,
        "step": 2,
        "round": 16
    },
    "timestamp": 1601658463943
}, {
    "time": 1524,
    "timeup": true,
    "done": true,
    "player": "861983579.062231",
    "stage": {
        "stage": 2,
        "step": 2,
        "round": 16
    },
    "timestamp": 1601658465433
}, {
    "time": 1553,
    "timeup": true,
    "done": true,
    "player": "653306322.0366257",
    "stage": {
        "stage": 2,
        "step": 2,
        "round": 16
    },
    "timestamp": 1601658465488
}]