[{
    "epoch": "tokenassignment",
    "trial": 57,
    "player": "283110650.8278265",
    "stage": {
        "stage": 3,
        "step": 2,
        "round": 57
    },
    "timestamp": 1601526865984
}, {
    "epoch": "tokenassignment",
    "trial": 57,
    "player": "809002888.1937599",
    "stage": {
        "stage": 3,
        "step": 2,
        "round": 57
    },
    "timestamp": 1601526865990
}, {
    "time": 1501,
    "timeup": true,
    "done": true,
    "player": "283110650.8278265",
    "stage": {
        "stage": 3,
        "step": 2,
        "round": 57
    },
    "timestamp": 1601526867487
}, {
    "time": 1501,
    "timeup": true,
    "done": true,
    "player": "809002888.1937599",
    "stage": {
        "stage": 3,
        "step": 2,
        "round": 57
    },
    "timestamp": 1601526867490
}]