[{
    "epoch": "tokenassignment",
    "trial": 74,
    "player": "592280108.1780387",
    "stage": {
        "stage": 3,
        "step": 2,
        "round": 74
    },
    "timestamp": 1601659346065
}, {
    "epoch": "tokenassignment",
    "trial": 74,
    "player": "160599159.6558778",
    "stage": {
        "stage": 3,
        "step": 2,
        "round": 74
    },
    "timestamp": 1601659346124
}, {
    "time": 1502,
    "timeup": true,
    "done": true,
    "player": "592280108.1780387",
    "stage": {
        "stage": 3,
        "step": 2,
        "round": 74
    },
    "timestamp": 1601659347540
}, {
    "time": 1555,
    "timeup": true,
    "done": true,
    "player": "160599159.6558778",
    "stage": {
        "stage": 3,
        "step": 2,
        "round": 74
    },
    "timestamp": 1601659347623
}]