[{
    "epoch": "tokenassignment",
    "trial": 69,
    "player": "597259999.5518095",
    "stage": {
        "stage": 3,
        "step": 2,
        "round": 69
    },
    "timestamp": 1601496542348
}, {
    "epoch": "tokenassignment",
    "trial": 69,
    "player": "528091607.3551285",
    "stage": {
        "stage": 3,
        "step": 2,
        "round": 69
    },
    "timestamp": 1601496542436
}, {
    "time": 1562,
    "timeup": true,
    "done": true,
    "player": "597259999.5518095",
    "stage": {
        "stage": 3,
        "step": 2,
        "round": 69
    },
    "timestamp": 1601496543870
}, {
    "time": 1527,
    "timeup": true,
    "done": true,
    "player": "528091607.3551285",
    "stage": {
        "stage": 3,
        "step": 2,
        "round": 69
    },
    "timestamp": 1601496543932
}]